pipeline/__init__.py
pipeline/admin.py
pipeline/apps.py
pipeline/builder/__init__.py
pipeline/builder/builder.py
pipeline/builder/flow/__init__.py
pipeline/builder/flow/activity.py
pipeline/builder/flow/base.py
pipeline/builder/flow/data.py
pipeline/builder/flow/event.py
pipeline/builder/flow/gateway.py
pipeline/celery/__init__.py
pipeline/celery/queues.py
pipeline/celery/settings.py
pipeline/component_framework/__init__.py
pipeline/component_framework/admin.py
pipeline/component_framework/apps.py
pipeline/component_framework/base.py
pipeline/component_framework/component.py
pipeline/component_framework/components/__init__.py
pipeline/component_framework/components/collections/__init__.py
pipeline/component_framework/components/collections/examples.py
pipeline/component_framework/constant.py
pipeline/component_framework/constants.py
pipeline/component_framework/context.py
pipeline/component_framework/library.py
pipeline/component_framework/management/__init__.py
pipeline/component_framework/management/commands/__init__.py
pipeline/component_framework/management/commands/run_component.py
pipeline/component_framework/management/commands/update_component_models.py
pipeline/component_framework/migrations/0001_initial.py
pipeline/component_framework/migrations/0002_delete_componentmodel.py
pipeline/component_framework/migrations/0003_componentmodel.py
pipeline/component_framework/migrations/0004_auto_20180413_1800.py
pipeline/component_framework/migrations/0005_auto_20190723_1806.py
pipeline/component_framework/migrations/0006_auto_20200213_0743.py
pipeline/component_framework/migrations/0007_auto_20201112_2244.py
pipeline/component_framework/migrations/0008_componentmodel_is_default_version.py
pipeline/component_framework/migrations/__init__.py
pipeline/component_framework/models.py
pipeline/component_framework/runner.py
pipeline/component_framework/test.py
pipeline/components/__init__.py
pipeline/components/collections/__init__.py
bamboo_pipeline-4.0.0.dist-info/LICENSE
bamboo_pipeline-4.0.0.dist-info/METADATA
bamboo_pipeline-4.0.0.dist-info/WHEEL
bamboo_pipeline-4.0.0.dist-info/RECORD
