Metadata-Version: 2.3
Name: bamboo-pipeline
Version: 4.0.0
Summary: runtime for bamboo-engine base on Django and Celery
License: MIT
Author: homholueng
Author-email: homholueng@gmail.com
Requires-Python: >=3.11,<3.12
Classifier: License :: OSI Approved :: MIT License
Classifier: Programming Language :: Python :: 3
Classifier: Programming Language :: Python :: 3.11
Requires-Dist: Django (>=4.2.0,<5)
Requires-Dist: Mako (>=1.3,<2.0)
Requires-Dist: Werkzeug (>=3,<4)
Requires-Dist: bamboo-engine (==3.0.1)
Requires-Dist: boto3 (>=1.34,<2.0)
Requires-Dist: celery (>=5.2.0,<6)
Requires-Dist: django-celery-beat (>=2.5,<3.0)
Requires-Dist: django-timezone-field (>=5,<6)
Requires-Dist: isodate (>=0.6,<0.7)
Requires-Dist: jsonschema (>=4.17.0,<5.0.0)
Requires-Dist: prometheus-client (>=0.20.0,<0.21.0)
Requires-Dist: pyparsing (>=3,<4)
Requires-Dist: pytz (>=2019.3)
Requires-Dist: redis (>=4.0.0,<6)
Requires-Dist: requests (>=2.31,<3.0)
Requires-Dist: ujson (>=5.9,<6.0)
